sequence_extensions/__init__.py
sequence_extensions/dict_ext.py
sequence_extensions/gen_ext.py
sequence_extensions/list_ext.py
sequence_extensions-0.1.4.dist-info/LICENSE
sequence_extensions-0.1.4.dist-info/METADATA
sequence_extensions-0.1.4.dist-info/WHEEL
sequence_extensions-0.1.4.dist-info/top_level.txt
sequence_extensions-0.1.4.dist-info/RECORD
