Metadata-Version: 2.1
Name: sequence-extensions
Version: 0.1.4
Summary: Higher order functions extension functins
Author: jkCXf9X4
Project-URL: Homepage, https://github.com/jkCXf9X4/sequence_extensions
Project-URL: Issues, https://github.com/pypa/sampleproject/issues
Classifier: Programming Language :: Python :: 3
Classifier: License :: OSI Approved :: MIT License
Classifier: Operating System :: OS Independent
Requires-Python: >=3.8
License-File: LICENSE
